.gitattributes
.gitignore
.pre-commit-config.yaml
LICENSE
MANIFEST.in
README.md
pyproject.toml
requirements.txt
setup.cfg
setup.py
.github/workflows/gh_pages.yml
.github/workflows/release.yml
.github/workflows/test.yml
autonomy_toolkit/__init__.py
autonomy_toolkit/_atk_base.py
autonomy_toolkit/_version.py
autonomy_toolkit/dev.py
autonomy_toolkit.egg-info/PKG-INFO
autonomy_toolkit.egg-info/SOURCES.txt
autonomy_toolkit.egg-info/dependency_links.txt
autonomy_toolkit.egg-info/entry_points.txt
autonomy_toolkit.egg-info/requires.txt
autonomy_toolkit.egg-info/top_level.txt
autonomy_toolkit/containers/__init__.py
autonomy_toolkit/containers/docker_client.py
autonomy_toolkit/utils/__init__.py
autonomy_toolkit/utils/atk_config.py
autonomy_toolkit/utils/files.py
autonomy_toolkit/utils/logger.py